tan313/__init__.py
tan313/setup.py
tan313-0.1.dist-info/LICENSE.txt
tan313-0.1.dist-info/METADATA
tan313-0.1.dist-info/WHEEL
tan313-0.1.dist-info/top_level.txt
tan313-0.1.dist-info/RECORD
