Metadata-Version: 2.1
Name: tan313
Version: 0.1
Summary: Python library for strong encryption by team ash
Author: TAN
Classifier: Programming Language :: Python :: 3
Classifier: Operating System :: OS Independent
Classifier: License :: OSI Approved :: MIT License
Requires-Python: >=3.6
License-File: LICENSE.txt
